Changelog
MANIFEST.in
distribute_setup.py
setup.py
bin/fbf
bin/fbf-fleet
bin/fbf-irc
bin/fbf-sleek
bin/fbf-tornado
fbf/__init__.py
fbf/imports.py
fbf/memcached.py
fbf/version.py
fbf/api/__init__.py
fbf/api/hooks.py
fbf/api/server.py
fbf/contrib/__init__.py
fbf/contrib/feedparser.py
fbf/contrib/memcache.py
fbf/contrib/rijndael.py
fbf/contrib/sgmllib.py
fbf/contrib/sgmllib3.py
fbf/contrib/bs4/__init__.py
fbf/contrib/bs4/dammit.py
fbf/contrib/bs4/element.py
fbf/contrib/bs4/testing.py
fbf/contrib/bs4/builder/__init__.py
fbf/contrib/bs4/builder/_html5lib.py
fbf/contrib/bs4/builder/_htmlparser.py
fbf/contrib/bs4/builder/_lxml.py
fbf/contrib/natural/__init__.py
fbf/contrib/natural/constant.py
fbf/contrib/natural/data.py
fbf/contrib/natural/date.py
fbf/contrib/natural/file.py
fbf/contrib/natural/number.py
fbf/contrib/natural/size.py
fbf/contrib/natural/text.py
fbf/contrib/natural/locale/af_ZA/LC_MESSAGES/natural.mo
fbf/contrib/natural/locale/de_DE/LC_MESSAGES/natural.mo
fbf/contrib/natural/locale/en_GB/LC_MESSAGES/natural.mo
fbf/contrib/natural/locale/en_US/LC_MESSAGES/natural.mo
fbf/contrib/natural/locale/es_ES/LC_MESSAGES/natural.mo
fbf/contrib/natural/locale/fr_FR/LC_MESSAGES/natural.mo
fbf/contrib/natural/locale/nl_NL/LC_MESSAGES/natural.mo
fbf/contrib/natural/templatetags/__init__.py
fbf/contrib/natural/templatetags/naturalise.py
fbf/contrib/natural/templatetags/naturalize.py
fbf/contrib/sleekxmpp/__init__.py
fbf/contrib/sleekxmpp/basexmpp.py
fbf/contrib/sleekxmpp/clientxmpp.py
fbf/contrib/sleekxmpp/componentxmpp.py
fbf/contrib/sleekxmpp/exceptions.py
fbf/contrib/sleekxmpp/version.py
fbf/contrib/sleekxmpp/features/__init__.py
fbf/contrib/sleekxmpp/features/feature_bind/__init__.py
fbf/contrib/sleekxmpp/features/feature_bind/bind.py
fbf/contrib/sleekxmpp/features/feature_bind/stanza.py
fbf/contrib/sleekxmpp/features/feature_mechanisms/__init__.py
fbf/contrib/sleekxmpp/features/feature_mechanisms/mechanisms.py
fbfbot.egg-info/PKG-INFO
fbfbot.egg-info/SOURCES.txt
fbfbot.egg-info/dependency_links.txt
fbfbot.egg-info/not-zip-safe
fbfbot.egg-info/top_level.txt