Metadata-Version: 1.1
Name: fbfbot
Version: 0.2.2
Summary: The FeedBackFlow bot
Home-page: https://github.com/feedbackflow/fbfbot
Author: FeedBack Flow
Author-email: feedbackflow@gmail.com
License: MIT
Platform: UNKNOWN
Classifier: Development Status :: 3 - Alpha
Classifier: Environment :: Console
Classifier: Environment :: Other Environment
Classifier: Intended Audience :: Developers
Classifier: License :: OSI Approved :: MIT License
Classifier: Operating System :: Unix
Classifier: Programming Language :: Python
Classifier: Topic :: Communications :: Chat
Classifier: Topic :: Software Development :: Libraries :: Python Modules
